whoops-0.2.2.dist-info/RECORD
whoops-0.2.2.dist-info/DESCRIPTION.rst
whoops-0.2.2.dist-info/WHEEL
whoops-0.2.2.dist-info/top_level.txt
whoops-0.2.2.dist-info/metadata.json
whoops-0.2.2.dist-info/METADATA
whoops-0.2.2.dist-info/entry_points.txt
whoops/__init__.py
whoops/__main__.py
