Metadata-Version: 2.0
Name: whoops
Version: 0.2.2
Summary: WebHDFS client
Home-page: https://bitbucket.org/tebeka/whoops
Author: Miki Tebeka
Author-email: miki.tebeka@gmail.com
License: MIT
Platform: UNKNOWN
Classifier: Development Status :: 4 - Beta
Classifier: Intended Audience :: Developers
Classifier: License :: OSI Approved :: MIT License
Classifier: Programming Language :: Python
Classifier: Programming Language :: Python :: 2
Classifier: Programming Language :: Python :: 3
Classifier: Topic :: Software Development :: Libraries
Classifier: Topic :: Software Development :: Libraries :: Python Modules
Requires-Dist: requests
